README.rst
setup.py
Argaeus.egg-info/PKG-INFO
Argaeus.egg-info/SOURCES.txt
Argaeus.egg-info/dependency_links.txt
Argaeus.egg-info/entry_points.txt
Argaeus.egg-info/requires.txt
Argaeus.egg-info/top_level.txt
argaeus/__init__.py
argaeus/thermostatguicontroller.py
argaeus/controller/__init__.py
argaeus/controller/acontroller.py
argaeus/controller/busyledcontroller.py
argaeus/controller/controllermanager.py
argaeus/controller/operationcontroller.py
argaeus/controller/setpointcontroller.py
argaeus/controller/behavior/__init__.py
argaeus/controller/behavior/behavior.py
argaeus/controller/behavior/behaviorcontroller.py
argaeus/controller/behavior/behaviorworker.py
argaeus/controller/behavior/buttonbehavior.py
argaeus/controller/modes/__init__.py
argaeus/controller/modes/aprogram.py
argaeus/controller/modes/modecontroller.py
argaeus/controller/modes/modefactory.py
argaeus/controller/modes/programschedule.py
argaeus/controller/modes/programsingle.py
argaeus/controller/modes/schedule_image.py
argaeus/controller/modes/setpoint.py
argaeus/schema/__init__.py
argaeus/schema/modecontroller.py
argaeus/schema/modeprogram.py
argaeus/schema/modeschedule.py
argaeus/schema/operationcontroller.py
argaeus/schema/setpointcontroller.py
argaeus/schema/thermostatguicontroller.py
tests_unit/__init__.py
tests_unit/test_modecontroller.py
tests_unit/test_modefactory.py
tests_unit/test_operationcontroller.py
tests_unit/test_programschedule.py
tests_unit/test_programsingle.py
tests_unit/test_schedule_image.py
tests_unit/test_setpoint.py
tests_unit/test_setpointcontroller.py
tests_unit/test_thermostatguicontroller.py
tests_unit/test_validateconfig.py