Metadata-Version: 1.2
Name: Argaeus
Version: 0.1.10
Summary: ThermostatGUIController (display and gui-logic) for a thermostat - to be used in combination with pelops/copreus and pelops/alcathous
Home-page: https://gitlab.com/pelops/argaeus/
Author: Tobias Gawron-Deutsch
Author-email: tobias@strix.at
License: MIT license
Keywords: mqtt microservice thermostat controller
Platform: UNKNOWN
Classifier: Development Status :: 4 - Beta
Classifier: Environment :: Console
Classifier: Environment :: No Input/Output (Daemon)
Classifier: Intended Audience :: Developers
Classifier: Programming Language :: Python :: 3
Classifier: Topic :: Utilities
Classifier: Topic :: Home Automation
Classifier: License :: OSI Approved :: MIT License
Requires-Python: >=3.5
